fouine/__init__.py
fouine/_download.py
fouine-0.0.2.dist-info/LICENSE.md
fouine-0.0.2.dist-info/METADATA
fouine-0.0.2.dist-info/WHEEL
fouine-0.0.2.dist-info/top_level.txt
fouine-0.0.2.dist-info/RECORD
