Metadata-Version: 2.1
Name: fouine
Version: 0.0.2
Summary: A tiny download function that does the maximum
Home-page: https://github.com/LoicGrobol/fouine
Author: Loïc Grobol
Author-email: loic.grobol@gmail.com
License: MIT
Platform: UNKNOWN
Classifier: Development Status :: 2 - Pre-Alpha
Classifier: License :: OSI Approved :: MIT License
Classifier: Programming Language :: Python :: 3.7
Classifier: Programming Language :: Python :: 3.8
Requires-Python: >=3.7
Requires-Dist: requests
Requires-Dist: tqdm
Requires-Dist: typing-extensions
